app/__init__.py
app/api.py
app/cli.py
app/table.py
fred_cli-1.0.0.dist-info/LICENSE
fred_cli-1.0.0.dist-info/METADATA
fred_cli-1.0.0.dist-info/WHEEL
fred_cli-1.0.0.dist-info/entry_points.txt
fred_cli-1.0.0.dist-info/top_level.txt
fred_cli-1.0.0.dist-info/RECORD
