Metadata-Version: 2.1
Name: fred-cli
Version: 1.0.0
Summary: CLI app powered by FRED (Federal Reserve Economic Data)
Home-page: https://github.com/aamnv/fred-cli
Author: aamnv
Author-email: aadithyan.manivannan@gmail.com
License: UNKNOWN
Platform: UNKNOWN
Requires-Python: >=3.6
Requires-Dist: Click
Requires-Dist: fred
Requires-Dist: tabulate
